sphinx_nested_apidoc-1.2.7.dist-info/METADATA
sphinx_nested_apidoc-1.2.7.dist-info/WHEEL
sphinx_nested_apidoc-1.2.7.dist-info/entry_points.txt
sphinx_nested_apidoc-1.2.7.dist-info/licenses/LICENSE
sphinx_nested_apidoc/__init__.py
sphinx_nested_apidoc/__main__.py
sphinx_nested_apidoc/_ext.py
sphinx_nested_apidoc/_version.py
sphinx_nested_apidoc/core.py
sphinx_nested_apidoc-1.2.7.dist-info/RECORD
