Metadata-Version: 2.1
Name: sphinx-nested-apidoc
Version: 1.2.7
Summary: sphinx-nested-apidoc: When flattened is not enough
Author-Email: Arunanshu Biswas <mydellpc07@gmail.com>
License: MIT
Classifier: Programming Language :: Python :: 3
Classifier: Programming Language :: Python :: 3.9
Classifier: Programming Language :: Python :: 3.10
Classifier: Programming Language :: Python :: 3.11
Classifier: Programming Language :: Python :: 3.12
Classifier: License :: OSI Approved :: MIT License
Classifier: Operating System :: OS Independent
Classifier: Intended Audience :: Developers
Classifier: Topic :: Documentation :: Sphinx
Project-URL: Bug tracker, https://github.com/arunanshub/sphinx-nested-apidoc/issues
Project-URL: Changelog, https://github.com/arunanshub/sphinx-nested-apidoc/blob/master/CHANGELOG.md
Project-URL: Repository, https://github.com/arunanshub/sphinx-nested-apidoc
Requires-Python: >=3.9
Requires-Dist: sphinx>=7.1.2
